canscan/__init__.py
canscan/__main__.py
canscan/node.py
canScan-0.0.2.dist-info/METADATA
canScan-0.0.2.dist-info/WHEEL
canScan-0.0.2.dist-info/top_level.txt
canScan-0.0.2.dist-info/zip-safe
canScan-0.0.2.dist-info/RECORD
