Metadata-Version: 2.1
Name: canScan
Version: 0.0.2
Summary: CANopen discovery tool/scanner
Home-page: https://github.com/dankamongmen/canscan
Author: Nick Black
Author-email: nickblack@linux.com
License: Apache License, Version 2.0
Keywords: CAN CANopen scanner
Platform: any
Classifier: Development Status :: 3 - Alpha
Classifier: Environment :: Console
Classifier: License :: OSI Approved :: Apache Software License
Classifier: Natural Language :: English
Classifier: Programming Language :: Python
Requires-Dist: canopen (>=0.9.0)
